clinical_listings/__init__.py
clinical_listings/formatting.py
clinical_listings/listings.py
clinical_listings/loader.py
clinical_listings/utils.py
clinical_listings-0.1.0.dist-info/METADATA
clinical_listings-0.1.0.dist-info/WHEEL
clinical_listings-0.1.0.dist-info/entry_points.txt
clinical_listings-0.1.0.dist-info/top_level.txt
clinical_listings-0.1.0.dist-info/RECORD
