Metadata-Version: 2.1
Name: clinical-listings
Version: 0.1.0
Summary: A package for creating formatted clinical trial listings.
Home-page: https://github.com/yourusername/clinical_listings
Author: Your Name
Author-email: your.email@example.com
Classifier: Programming Language :: Python :: 3
Classifier: License :: OSI Approved :: MIT License
Classifier: Operating System :: OS Independent
Requires-Python: >=3.6
Requires-Dist: pandas
Requires-Dist: numpy
Requires-Dist: sqlalchemy
Requires-Dist: sas7bdat
Requires-Dist: reportlab
Requires-Dist: fpdf
